eventListen/__init__.py
eventListen/eventListen.py
eventListen-0.1.2.dist-info/LICENSE
eventListen-0.1.2.dist-info/METADATA
eventListen-0.1.2.dist-info/WHEEL
eventListen-0.1.2.dist-info/top_level.txt
eventListen-0.1.2.dist-info/RECORD
