Metadata-Version: 2.2
Name: eventListen
Version: 0.1.2
Summary: eventListen is a small module for creating events.
Author-email: Artic <artic.admisoffi@gmail.com>
Project-URL: Homepage, https://github.com/ArticOff/eventListen
Classifier: Programming Language :: Python :: 3
Classifier: License :: OSI Approved :: GNU General Public License v3 (GPLv3)
Classifier: Operating System :: OS Independent
Requires-Python: >=3.10
License-File: LICENSE
Requires-Dist: proto-obj>=0.0.4
